syotools/__init__.py
syotools/coronagraph/__init__.py
syotools/coronagraph/coron_model.py
syotools/coronagraph/coron_model_v1.py
syotools/coronagraph/coron_model_v2.py
syotools/coronagraph/coron_model_v3.py
syotools/coronagraph/luvoir_demo.py
syotools/defaults/__init__.py
syotools/defaults/model_defaults.py
syotools/defaults/model_defaults.yaml
syotools/interface/__init__.py
syotools/interface/_std_factory.py
syotools/interface/base.py
syotools/interface/factory.py
syotools/models/__init__.py
syotools/models/base.py
syotools/models/camera.py
syotools/models/coronagraph.py
syotools/models/exposure.py
syotools/models/scene.py
syotools/models/source.py
syotools/models/source_exposure.py
syotools/models/spectrograph.py
syotools/models/telescope.py
syotools/persistence/__init__.py
syotools/persistence/json_protocol.py
syotools/persistence/protocol.py
syotools/reference_data/10Myr_Starburst_nodust.dat
syotools/reference_data/CTTS_etc_d140pc_101116.txt
syotools/reference_data/LINER_template.txt
syotools/reference_data/LUMOS_ETC.fits
syotools/reference_data/POLLUX_ETC.fits
syotools/reference_data/Seyfert_1_template.txt
syotools/reference_data/Seyfert_2_template.txt
syotools/reference_data/dG_d5pc_pollux.txt
syotools/reference_data/dM1_etc_d5pc_101116.txt
syotools/reference_data/dM_d1pc_pollux.txt
syotools/reference_data/earth_quadrature_radiance_refl.dat
syotools/reference_data/ttauri.txt
syotools/reference_data/fesc/fe_lyccontrot0.001hi1.000hei.txt
syotools/reference_data/fesc/fe_lyccontrot0.010hi1.000hei.txt
syotools/reference_data/fesc/fe_lyccontrot0.100hi1.000hei.txt
syotools/reference_data/fesc/fe_lyccontrot1.000hi0.001hei.txt
syotools/reference_data/fesc/fe_lyccontrot1.000hi1.000hei.txt
syotools/reference_data/pysynphot_data/__init__.py
syotools/reference_data/pysynphot_data/calspec/g191b2b_mod_010.fits
syotools/reference_data/pysynphot_data/calspec/gd153_fos_003.fits
syotools/reference_data/pysynphot_data/calspec/gd71_fos_003.fits
syotools-1.3.0.dist-info/METADATA
syotools-1.3.0.dist-info/WHEEL
syotools-1.3.0.dist-info/top_level.txt
syotools-1.3.0.dist-info/RECORD
