Metadata-Version: 2.4
Name: syotools
Version: 1.3.0
Summary: Science Yield Optimization Tools (SYOTools)
Author-email: "Jason Tumlinson, STScI" <tumlinson@stsci.edu>
License-Expression: BSD-3-Clause
Project-URL: Homepage, https://github.com/spacetelescope/hwo-tools
Keywords: simulation,astronomy,astrophysics
Classifier: Programming Language :: Python :: 3.10
Requires-Python: >=3.10
Requires-Dist: hwo_sci_eng==0.1.9
Requires-Dist: astropy>6
Requires-Dist: synphot
Requires-Dist: stsynphot
Requires-Dist: numpy
Requires-Dist: scipy
Requires-Dist: specutils
Provides-Extra: dev
Requires-Dist: pytest>=8.3.4; extra == "dev"
Requires-Dist: pytest-env>=1.1.5; extra == "dev"
